cool_lib/__init__.py
cool_lib/__main__.py
cool_lib/a.py
cool_lib/b.py
blurp-0.4.dist-info/METADATA
blurp-0.4.dist-info/WHEEL
blurp-0.4.dist-info/entry_points.txt
blurp-0.4.dist-info/top_level.txt
blurp-0.4.dist-info/RECORD
