Metadata-Version: 2.1
Name: blurp
Version: 0.4
Summary: simples example in the python world
Home-page: https://github.com/gdamjan/hello-world-python-package
Author: x@x.com
Author-email: x@x.com
License: MIT
Platform: UNKNOWN
